{"pdf_page": 212, "w": 1434, "h": 2330, "dpi": 300, "blocks": [{"order": 0, "label": "PageHeader", "conf": 0.995, "html": "Mangala Gaur]", "bbox": [129.06, 102.52, 453.144, 151.45000000000002]}, {"order": 1, "label": "PageHeader", "conf": 0.995, "html": "HINDU HOLIDAYS", "bbox": [532.014, 107.17999999999999, 887.646, 144.46]}, {"order": 2, "label": "Text", "conf": 0.995, "html": "<p>husband's instructions, but on throwing the food into the <i>jholi</i>, she saw that the saintly person was exasperated beyond measure. He even went so far as to say, 'O you wicked one! You, the wife of a sonless man, you, the curse of your race, you are a disgrace to your family'—and so forth. He became abusive and so vexed that it was feared he would curse the lady. Her husband dressed as a farmer followed the irate old man to the river, where he forthwith went to wash his towel. While performing the tedious operation of removing the rice that was found sticking to the cloth, he gave full vent to his feelings and showered abuses on the poor woman. Her husband was near, he offered his services, got into conversation with him, and asked him why he threw away the rich, princely dish that was offered to him so devotedly by the Bania lady. 'Oh! but she is a <i>nīputrik</i>, a woman without a son,' said the old man, grinding his teeth. It is against the <i>shāstras</i> to accept food from people who have no sons born unto them. What can the Bania do to get a son, was the earnest question, and the saint advised that the Bania should go to a certain temple on a certain hill and perform austerities in front of the goddess there. They parted. The Bania returned home and left for the temple. In course of time he performed the austerities and the goddess appeared before him as usual. She asked him to name the blessing he would desire; he mentioned—<i>a son</i>. She said that there was no son nor even a daughter in his <i>karma</i> or <i>takhdir</i>, but that as he performed the austerities so faithfully, she would grant one boon. He should select it from the offer she was just going to make. It ran: 'If you get a son he will be short-lived and die at the end of the sixteenth year, but if you accept a daughter she will live long but will become a child-widow. Choose,' added the goddess. There was no hesitation and no time was required for consideration</p>", "bbox": [124.758, 195.72, 1317.846, 2090.01]}, {"order": 3, "label": "PageFooter", "conf": 0.995, "html": "152", "bbox": [692.622, 2113.31, 770.058, 2157.58]}]}